{"type":"FeatureCollection","features":[{"type":"Feature","properties":{"referenceFormID":"00038C21"},"geometry":{"type":"Point","coordinates":[27080,14355]}},{"type":"Feature","properties":{"referenceFormID":"00038C21"},"geometry":{"type":"Point","coordinates":[58539,71176]}},{"type":"Feature","properties":{"referenceFormID":"00038C21"},"geometry":{"type":"Point","coordinates":[91281,20226]}},{"type":"Feature","properties":{"referenceFormID":"00038C21"},"geometry":{"type":"Point","coordinates":[69023,75956]}},{"type":"Feature","properties":{"referenceFormID":"00038C21"},"geometry":{"type":"Point","coordinates":[2570,-68396]}},{"type":"Feature","properties":{"referenceFormID":"00038C21"},"geometry":{"type":"Point","coordinates":[29093,-46830]}},{"type":"Feature","properties":{"referenceFormID":"00038C21"},"geometry":{"type":"Point","coordinates":[26652,-41854]}},{"type":"Feature","properties":{"referenceFormID":"00038C21"},"geometry":{"type":"Point","coordinates":[21234,-6859]}},{"type":"Feature","properties":{"referenceFormID":"00038C21"},"geometry":{"type":"Point","coordinates":[16886,-16016]}},{"type":"Feature","properties":{"referenceFormID":"00038C21"},"geometry":{"type":"Point","coordinates":[16111,-15796]}},{"type":"Feature","properties":{"referenceFormID":"00038C21"},"geometry":{"type":"Point","coordinates":[11229,-22803]}},{"type":"Feature","properties":{"referenceFormID":"00038C21"},"geometry":{"type":"Point","coordinates":[40424,-31871]}},{"type":"Feature","properties":{"referenceFormID":"00038C21"},"geometry":{"type":"Point","coordinates":[77912,-66768]}},{"type":"Feature","properties":{"referenceFormID":"00038C21"},"geometry":{"type":"Point","coordinates":[86472,-49441]}},{"type":"Feature","properties":{"referenceFormID":"00038C21"},"geometry":{"type":"Point","coordinates":[84820,-62742]}},{"type":"Feature","properties":{"referenceFormID":"00038C21"},"geometry":{"type":"Point","coordinates":[162325,2113]}},{"type":"Feature","properties":{"referenceFormID":"00038C21"},"geometry":{"type":"Point","coordinates":[156485,2012]}},{"type":"Feature","properties":{"referenceFormID":"00038C21"},"geometry":{"type":"Point","coordinates":[166004,2571]}},{"type":"Feature","properties":{"referenceFormID":"00038C21"},"geometry":{"type":"Point","coordinates":[195258,103565]}},{"type":"Feature","properties":{"referenceFormID":"00038C21"},"geometry":{"type":"Point","coordinates":[197420,99117]}},{"type":"Feature","properties":{"referenceFormID":"00038C21"},"geometry":{"type":"Point","coordinates":[179657,-142046]}},{"type":"Feature","properties":{"referenceFormID":"00038C21"},"geometry":{"type":"Point","coordinates":[179405,-141822]}},{"type":"Feature","properties":{"referenceFormID":"00038C21"},"geometry":{"type":"Point","coordinates":[179425,-147834]}},{"type":"Feature","properties":{"referenceFormID":"00038C21"},"geometry":{"type":"Point","coordinates":[159734,-38325]}},{"type":"Feature","properties":{"referenceFormID":"00038C21"},"geometry":{"type":"Point","coordinates":[162186,-3645]}},{"type":"Feature","properties":{"referenceFormID":"00038C21"},"geometry":{"type":"Point","coordinates":[156152,-444]}},{"type":"Feature","properties":{"referenceFormID":"00038C21"},"geometry":{"type":"Point","coordinates":[155236,-20482]}},{"type":"Feature","properties":{"referenceFormID":"00038C21"},"geometry":{"type":"Point","coordinates":[176806,-91661]}},{"type":"Feature","properties":{"referenceFormID":"00038C21"},"geometry":{"type":"Point","coordinates":[189706,-62497]}},{"type":"Feature","properties":{"referenceFormID":"00038C21"},"geometry":{"type":"Point","coordinates":[198912,-97143]}},{"type":"Feature","properties":{"referenceFormID":"00038C21"},"geometry":{"type":"Point","coordinates":[-146798,32810]}},{"type":"Feature","properties":{"referenceFormID":"00038C21"},"geometry":{"type":"Point","coordinates":[-159656,108584]}},{"type":"Feature","properties":{"referenceFormID":"00038C21"},"geometry":{"type":"Point","coordinates":[-157884,-131754]}},{"type":"Feature","properties":{"referenceFormID":"00038C21"},"geometry":{"type":"Point","coordinates":[-189093,-119868]}},{"type":"Feature","properties":{"referenceFormID":"00038C21"},"geometry":{"type":"Point","coordinates":[-164795,-52753]}},{"type":"Feature","properties":{"referenceFormID":"00038C21"},"geometry":{"type":"Point","coordinates":[-136550,-121862]}},{"type":"Feature","properties":{"referenceFormID":"00038C21"},"geometry":{"type":"Point","coordinates":[-135509,-48304]}},{"type":"Feature","properties":{"referenceFormID":"00038C21"},"geometry":{"type":"Point","coordinates":[-140969,-56688]}},{"type":"Feature","properties":{"referenceFormID":"00038C21"},"geometry":{"type":"Point","coordinates":[-98792,7740]}},{"type":"Feature","properties":{"referenceFormID":"00038C21"},"geometry":{"type":"Point","coordinates":[-106768,28520]}},{"type":"Feature","properties":{"referenceFormID":"00038C21"},"geometry":{"type":"Point","coordinates":[-118318,16773]}},{"type":"Feature","properties":{"referenceFormID":"00038C21"},"geometry":{"type":"Point","coordinates":[-119385,16280]}},{"type":"Feature","properties":{"referenceFormID":"00038C21"},"geometry":{"type":"Point","coordinates":[-119447,40671]}},{"type":"Feature","properties":{"referenceFormID":"00038C21"},"geometry":{"type":"Point","coordinates":[-97665,31883]}},{"type":"Feature","properties":{"referenceFormID":"00038C21"},"geometry":{"type":"Point","coordinates":[-59365,92158]}},{"type":"Feature","properties":{"referenceFormID":"00038C21"},"geometry":{"type":"Point","coordinates":[-21974,48681]}},{"type":"Feature","properties":{"referenceFormID":"00038C21"},"geometry":{"type":"Point","coordinates":[-9132,88728]}},{"type":"Feature","properties":{"referenceFormID":"00038C21"},"geometry":{"type":"Point","coordinates":[-25185,89278]}},{"type":"Feature","properties":{"referenceFormID":"00038C21"},"geometry":{"type":"Point","coordinates":[-30587,90075]}},{"type":"Feature","properties":{"referenceFormID":"00038C21"},"geometry":{"type":"Point","coordinates":[-27163,129767]}},{"type":"Feature","properties":{"referenceFormID":"00038C21"},"geometry":{"type":"Point","coordinates":[-68552,208355]}},{"type":"Feature","properties":{"referenceFormID":"00038C21"},"geometry":{"type":"Point","coordinates":[-92759,205795]}},{"type":"Feature","properties":{"referenceFormID":"00038C21"},"geometry":{"type":"Point","coordinates":[-47416,144573]}},{"type":"Feature","properties":{"referenceFormID":"00038C21"},"geometry":{"type":"Point","coordinates":[-53060,147586]}},{"type":"Feature","properties":{"referenceFormID":"00038C21"},"geometry":{"type":"Point","coordinates":[-21580,164965]}},{"type":"Feature","properties":{"referenceFormID":"00038C21"},"geometry":{"type":"Point","coordinates":[-24591,167949]}},{"type":"Feature","properties":{"referenceFormID":"00038C21"},"geometry":{"type":"Point","coordinates":[-103396,-139798]}},{"type":"Feature","properties":{"referenceFormID":"00038C21"},"geometry":{"type":"Point","coordinates":[-104669,-140217]}},{"type":"Feature","properties":{"referenceFormID":"00038C21"},"geometry":{"type":"Point","coordinates":[-37661,-147489]}},{"type":"Feature","properties":{"referenceFormID":"00038C21"},"geometry":{"type":"Point","coordinates":[-55208,-131755]}},{"type":"Feature","properties":{"referenceFormID":"00038C21"},"geometry":{"type":"Point","coordinates":[-23209,-169321]}},{"type":"Feature","properties":{"referenceFormID":"00038C21"},"geometry":{"type":"Point","coordinates":[-118030,-122780]}},{"type":"Feature","properties":{"referenceFormID":"00038C21"},"geometry":{"type":"Point","coordinates":[-115875,-73878]}},{"type":"Feature","properties":{"referenceFormID":"00038C21"},"geometry":{"type":"Point","coordinates":[-107898,-47471]}},{"type":"Feature","properties":{"referenceFormID":"00038C21"},"geometry":{"type":"Point","coordinates":[-112233,-37290]}},{"type":"Feature","properties":{"referenceFormID":"00038C21"},"geometry":{"type":"Point","coordinates":[-116222,-42722]}},{"type":"Feature","properties":{"referenceFormID":"00038C21"},"geometry":{"type":"Point","coordinates":[-125072,-37275]}},{"type":"Feature","properties":{"referenceFormID":"00038C21"},"geometry":{"type":"Point","coordinates":[-125673,-54234]}},{"type":"Feature","properties":{"referenceFormID":"00038C21"},"geometry":{"type":"Point","coordinates":[-123446,-9909]}},{"type":"Feature","properties":{"referenceFormID":"00038C21"},"geometry":{"type":"Point","coordinates":[-69241,-42610]}},{"type":"Feature","properties":{"referenceFormID":"00038C21"},"geometry":{"type":"Point","coordinates":[-70821,-55677]}},{"type":"Feature","properties":{"referenceFormID":"00038C21"},"geometry":{"type":"Point","coordinates":[-79680,-62433]}},{"type":"Feature","properties":{"referenceFormID":"00038C21"},"geometry":{"type":"Point","coordinates":[-60620,-110235]}},{"type":"Feature","properties":{"referenceFormID":"00038C21"},"geometry":{"type":"Point","coordinates":[-43910,-18761]}},{"type":"Feature","properties":{"referenceFormID":"00038C21"},"geometry":{"type":"Point","coordinates":[-22899,-59220]}},{"type":"Feature","properties":{"referenceFormID":"00038C21"},"geometry":{"type":"Point","coordinates":[-22925,-59094]}},{"type":"Feature","properties":{"referenceFormID":"00038C21","lockLevel":"Advanced (Level 1)"},"geometry":{"type":"Point","coordinates":[33145,74027]}},{"type":"Feature","properties":{"referenceFormID":"00038C21","lockLevel":"Advanced (Level 1)"},"geometry":{"type":"Point","coordinates":[98753,94987]}},{"type":"Feature","properties":{"referenceFormID":"00038C21","lockLevel":"Advanced (Level 1)"},"geometry":{"type":"Point","coordinates":[21190,131730]}},{"type":"Feature","properties":{"referenceFormID":"00038C21","lockLevel":"Advanced (Level 1)"},"geometry":{"type":"Point","coordinates":[85908,131486]}},{"type":"Feature","properties":{"referenceFormID":"00038C21","lockLevel":"Advanced (Level 1)"},"geometry":{"type":"Point","coordinates":[115581,191242]}},{"type":"Feature","properties":{"referenceFormID":"00038C21","lockLevel":"Advanced (Level 1)"},"geometry":{"type":"Point","coordinates":[33749,-105727]}},{"type":"Feature","properties":{"referenceFormID":"00038C21","lockLevel":"Advanced (Level 1)"},"geometry":{"type":"Point","coordinates":[69368,-94891]}},{"type":"Feature","properties":{"referenceFormID":"00038C21","lockLevel":"Advanced (Level 1)"},"geometry":{"type":"Point","coordinates":[161512,-42719]}},{"type":"Feature","properties":{"referenceFormID":"00038C21","lockLevel":"Advanced (Level 1)"},"geometry":{"type":"Point","coordinates":[-41557,51012]}},{"type":"Feature","properties":{"referenceFormID":"00038C21","lockLevel":"Advanced (Level 1)"},"geometry":{"type":"Point","coordinates":[-27506,90261]}},{"type":"Feature","properties":{"referenceFormID":"00038C21","lockLevel":"Advanced (Level 1)"},"geometry":{"type":"Point","coordinates":[-93293,204866]}},{"type":"Feature","properties":{"referenceFormID":"00038C21","lockLevel":"Advanced (Level 1)"},"geometry":{"type":"Point","coordinates":[-15583,-44780]}},{"type":"Feature","properties":{"referenceFormID":"00038C21","lockLevel":"Expert (Level 2)"},"geometry":{"type":"Point","coordinates":[162249,-27476]}},{"type":"Feature","properties":{"referenceFormID":"00038C21","lockLevel":"Expert (Level 2)"},"geometry":{"type":"Point","coordinates":[144116,-26529]}},{"type":"Feature","properties":{"referenceFormID":"00038C21","lockLevel":"Expert (Level 2)"},"geometry":{"type":"Point","coordinates":[-132852,-135458]}},{"type":"Feature","properties":{"referenceFormID":"00038C21","lockLevel":"Expert (Level 2)"},"geometry":{"type":"Point","coordinates":[-45477,-22332]}},{"type":"Feature","properties":{"referenceFormID":"00038C21","lockLevel":"Novice (Level 0)"},"geometry":{"type":"Point","coordinates":[-58654,64932]}},{"type":"Feature","properties":{"referenceFormID":"00038C21","lockLevel":"Novice (Level 0)"},"geometry":{"type":"Point","coordinates":[-16439,176261]}},{"type":"Feature","properties":{"referenceFormID":"00038C21","lockLevel":"Opens Door"},"geometry":{"type":"Point","coordinates":[-147906,52002]}},{"type":"Feature","properties":{"referenceFormID":"00038C21","lockLevel":"Opens Door"},"geometry":{"type":"Point","coordinates":[180040,-141490]}},{"type":"Feature","properties":{"referenceFormID":"00038C21","lockLevel":"Opens Door"},"geometry":{"type":"Point","coordinates":[-9335,51115]}},{"type":"Feature","properties":{"referenceFormID":"00038C21","lockLevel":"Opens Door"},"geometry":{"type":"Point","coordinates":[-24181,167561]}}]}
