{"type":"FeatureCollection","features":[{"type":"Feature","properties":{"referenceFormID":"000A0F53"},"geometry":{"type":"Point","coordinates":[-92872,12467]}},{"type":"Feature","properties":{"referenceFormID":"000A0F53"},"geometry":{"type":"Point","coordinates":[-97970,8880]}},{"type":"Feature","properties":{"referenceFormID":"000A0F53"},"geometry":{"type":"Point","coordinates":[-104234,3447]}},{"type":"Feature","properties":{"referenceFormID":"000A0F53"},"geometry":{"type":"Point","coordinates":[-121186,-8670]}},{"type":"Feature","properties":{"referenceFormID":"000A0F53"},"geometry":{"type":"Point","coordinates":[-122356,-10505]}},{"type":"Feature","properties":{"referenceFormID":"000A0F53"},"geometry":{"type":"Point","coordinates":[-81856,16743]}},{"type":"Feature","properties":{"referenceFormID":"000A0F53"},"geometry":{"type":"Point","coordinates":[-80036,15700]}},{"type":"Feature","properties":{"referenceFormID":"000A0F53"},"geometry":{"type":"Point","coordinates":[-77812,15902]}},{"type":"Feature","properties":{"referenceFormID":"000A0F53"},"geometry":{"type":"Point","coordinates":[-82902,9365]}},{"type":"Feature","properties":{"referenceFormID":"000A0F53"},"geometry":{"type":"Point","coordinates":[-82565,13786]}},{"type":"Feature","properties":{"referenceFormID":"000A0F53"},"geometry":{"type":"Point","coordinates":[-82535,12342]}},{"type":"Feature","properties":{"referenceFormID":"000A0F53"},"geometry":{"type":"Point","coordinates":[-82383,12919]}},{"type":"Feature","properties":{"referenceFormID":"000A0F53"},"geometry":{"type":"Point","coordinates":[-83465,11799]}},{"type":"Feature","properties":{"referenceFormID":"000A0F53"},"geometry":{"type":"Point","coordinates":[-83130,12864]}},{"type":"Feature","properties":{"referenceFormID":"000A0F53"},"geometry":{"type":"Point","coordinates":[-83311,13552]}},{"type":"Feature","properties":{"referenceFormID":"000A0F53"},"geometry":{"type":"Point","coordinates":[83028,-40123]}},{"type":"Feature","properties":{"referenceFormID":"000A0F53"},"geometry":{"type":"Point","coordinates":[-81836,16696]}}]}
