{"type":"FeatureCollection","features":[{"type":"Feature","properties":{"referenceFormID":"001097E6"},"geometry":{"type":"Point","coordinates":[65329,196381]}},{"type":"Feature","properties":{"referenceFormID":"001097E6"},"geometry":{"type":"Point","coordinates":[63648,190144]}},{"type":"Feature","properties":{"referenceFormID":"001097E6"},"geometry":{"type":"Point","coordinates":[61184,191605]}},{"type":"Feature","properties":{"referenceFormID":"001097E6"},"geometry":{"type":"Point","coordinates":[39604,172357]}},{"type":"Feature","properties":{"referenceFormID":"001097E6"},"geometry":{"type":"Point","coordinates":[139892,111563]}},{"type":"Feature","properties":{"referenceFormID":"001097E6"},"geometry":{"type":"Point","coordinates":[139664,111977]}},{"type":"Feature","properties":{"referenceFormID":"001097E6"},"geometry":{"type":"Point","coordinates":[162867,-40885]}},{"type":"Feature","properties":{"referenceFormID":"001097E6","lockLevel":"Advanced (Level 1)"},"geometry":{"type":"Point","coordinates":[60766,191454]}}]}
