{"type":"FeatureCollection","features":[{"type":"Feature","properties":{"referenceFormID":"0035D21C"},"geometry":{"type":"Point","coordinates":[31291,24594]}},{"type":"Feature","properties":{"referenceFormID":"0035D21C"},"geometry":{"type":"Point","coordinates":[32488,15812]}},{"type":"Feature","properties":{"referenceFormID":"0035D21C"},"geometry":{"type":"Point","coordinates":[28571,23512]}},{"type":"Feature","properties":{"referenceFormID":"0035D21C"},"geometry":{"type":"Point","coordinates":[14137,1058]}},{"type":"Feature","properties":{"referenceFormID":"0035D21C"},"geometry":{"type":"Point","coordinates":[31075,98209]}},{"type":"Feature","properties":{"referenceFormID":"0035D21C"},"geometry":{"type":"Point","coordinates":[28472,85892]}},{"type":"Feature","properties":{"referenceFormID":"0035D21C"},"geometry":{"type":"Point","coordinates":[42684,32199]}},{"type":"Feature","properties":{"referenceFormID":"0035D21C"},"geometry":{"type":"Point","coordinates":[52632,48508]}},{"type":"Feature","properties":{"referenceFormID":"0035D21C"},"geometry":{"type":"Point","coordinates":[47344,59098]}},{"type":"Feature","properties":{"referenceFormID":"0035D21C"},"geometry":{"type":"Point","coordinates":[59209,86283]}},{"type":"Feature","properties":{"referenceFormID":"0035D21C"},"geometry":{"type":"Point","coordinates":[59232,86252]}},{"type":"Feature","properties":{"referenceFormID":"0035D21C"},"geometry":{"type":"Point","coordinates":[49374,70190]}},{"type":"Feature","properties":{"referenceFormID":"0035D21C"},"geometry":{"type":"Point","coordinates":[49346,70168]}},{"type":"Feature","properties":{"referenceFormID":"0035D21C"},"geometry":{"type":"Point","coordinates":[40352,89941]}},{"type":"Feature","properties":{"referenceFormID":"0035D21C"},"geometry":{"type":"Point","coordinates":[94847,12652]}},{"type":"Feature","properties":{"referenceFormID":"0035D21C"},"geometry":{"type":"Point","coordinates":[97638,14738]}},{"type":"Feature","properties":{"referenceFormID":"0035D21C"},"geometry":{"type":"Point","coordinates":[89139,25136]}},{"type":"Feature","properties":{"referenceFormID":"0035D21C"},"geometry":{"type":"Point","coordinates":[89165,25144]}},{"type":"Feature","properties":{"referenceFormID":"0035D21C"},"geometry":{"type":"Point","coordinates":[77126,2021]}},{"type":"Feature","properties":{"referenceFormID":"0035D21C"},"geometry":{"type":"Point","coordinates":[95125,49370]}},{"type":"Feature","properties":{"referenceFormID":"0035D21C"},"geometry":{"type":"Point","coordinates":[95149,49349]}},{"type":"Feature","properties":{"referenceFormID":"0035D21C"},"geometry":{"type":"Point","coordinates":[86724,62822]}},{"type":"Feature","properties":{"referenceFormID":"0035D21C"},"geometry":{"type":"Point","coordinates":[83455,58088]}},{"type":"Feature","properties":{"referenceFormID":"0035D21C"},"geometry":{"type":"Point","coordinates":[83443,58093]}},{"type":"Feature","properties":{"referenceFormID":"0035D21C"},"geometry":{"type":"Point","coordinates":[72608,64937]}},{"type":"Feature","properties":{"referenceFormID":"0035D21C"},"geometry":{"type":"Point","coordinates":[66864,46670]}},{"type":"Feature","properties":{"referenceFormID":"0035D21C"},"geometry":{"type":"Point","coordinates":[97024,81358]}},{"type":"Feature","properties":{"referenceFormID":"0035D21C"},"geometry":{"type":"Point","coordinates":[82189,83910]}},{"type":"Feature","properties":{"referenceFormID":"0035D21C"},"geometry":{"type":"Point","coordinates":[70642,73278]}},{"type":"Feature","properties":{"referenceFormID":"0035D21C"},"geometry":{"type":"Point","coordinates":[96897,128406]}},{"type":"Feature","properties":{"referenceFormID":"0035D21C"},"geometry":{"type":"Point","coordinates":[90158,105515]}},{"type":"Feature","properties":{"referenceFormID":"0035D21C"},"geometry":{"type":"Point","coordinates":[89367,111692]}},{"type":"Feature","properties":{"referenceFormID":"0035D21C"},"geometry":{"type":"Point","coordinates":[74731,103459]}},{"type":"Feature","properties":{"referenceFormID":"0035D21C"},"geometry":{"type":"Point","coordinates":[113497,23557]}},{"type":"Feature","properties":{"referenceFormID":"0035D21C"},"geometry":{"type":"Point","coordinates":[104058,11194]}},{"type":"Feature","properties":{"referenceFormID":"0035D21C"},"geometry":{"type":"Point","coordinates":[124951,37453]}},{"type":"Feature","properties":{"referenceFormID":"0035D21C"},"geometry":{"type":"Point","coordinates":[108447,62848]}},{"type":"Feature","properties":{"referenceFormID":"0035D21C"},"geometry":{"type":"Point","coordinates":[108122,62297]}},{"type":"Feature","properties":{"referenceFormID":"0035D21C"},"geometry":{"type":"Point","coordinates":[107883,35966]}},{"type":"Feature","properties":{"referenceFormID":"0035D21C"},"geometry":{"type":"Point","coordinates":[106397,35985]}},{"type":"Feature","properties":{"referenceFormID":"0035D21C"},"geometry":{"type":"Point","coordinates":[116817,82818]}},{"type":"Feature","properties":{"referenceFormID":"0035D21C"},"geometry":{"type":"Point","coordinates":[117900,84346]}},{"type":"Feature","properties":{"referenceFormID":"0035D21C"},"geometry":{"type":"Point","coordinates":[117624,80975]}},{"type":"Feature","properties":{"referenceFormID":"0035D21C"},"geometry":{"type":"Point","coordinates":[114606,82574]}},{"type":"Feature","properties":{"referenceFormID":"0035D21C"},"geometry":{"type":"Point","coordinates":[113013,81020]}},{"type":"Feature","properties":{"referenceFormID":"0035D21C"},"geometry":{"type":"Point","coordinates":[112193,75322]}},{"type":"Feature","properties":{"referenceFormID":"0035D21C"},"geometry":{"type":"Point","coordinates":[107998,76740]}},{"type":"Feature","properties":{"referenceFormID":"0035D21C"},"geometry":{"type":"Point","coordinates":[99021,83326]}},{"type":"Feature","properties":{"referenceFormID":"0035D21C"},"geometry":{"type":"Point","coordinates":[102578,111653]}},{"type":"Feature","properties":{"referenceFormID":"0035D21C"},"geometry":{"type":"Point","coordinates":[103754,109486]}},{"type":"Feature","properties":{"referenceFormID":"0035D21C"},"geometry":{"type":"Point","coordinates":[102161,108692]}},{"type":"Feature","properties":{"referenceFormID":"0035D21C"},"geometry":{"type":"Point","coordinates":[100981,107511]}},{"type":"Feature","properties":{"referenceFormID":"0035D21C"},"geometry":{"type":"Point","coordinates":[99800,106517]}},{"type":"Feature","properties":{"referenceFormID":"0035D21C"},"geometry":{"type":"Point","coordinates":[101177,104726]}},{"type":"Feature","properties":{"referenceFormID":"0035D21C"},"geometry":{"type":"Point","coordinates":[29942,149584]}},{"type":"Feature","properties":{"referenceFormID":"0035D21C"},"geometry":{"type":"Point","coordinates":[60824,142015]}},{"type":"Feature","properties":{"referenceFormID":"0035D21C"},"geometry":{"type":"Point","coordinates":[56233,141582]}},{"type":"Feature","properties":{"referenceFormID":"0035D21C"},"geometry":{"type":"Point","coordinates":[48147,194855]}},{"type":"Feature","properties":{"referenceFormID":"0035D21C"},"geometry":{"type":"Point","coordinates":[63179,202362]}},{"type":"Feature","properties":{"referenceFormID":"0035D21C"},"geometry":{"type":"Point","coordinates":[61395,200710]}},{"type":"Feature","properties":{"referenceFormID":"0035D21C"},"geometry":{"type":"Point","coordinates":[47053,197598]}},{"type":"Feature","properties":{"referenceFormID":"0035D21C"},"geometry":{"type":"Point","coordinates":[47039,197650]}},{"type":"Feature","properties":{"referenceFormID":"0035D21C"},"geometry":{"type":"Point","coordinates":[44405,197911]}},{"type":"Feature","properties":{"referenceFormID":"0035D21C"},"geometry":{"type":"Point","coordinates":[91081,149969]}},{"type":"Feature","properties":{"referenceFormID":"0035D21C"},"geometry":{"type":"Point","coordinates":[95838,169536]}},{"type":"Feature","properties":{"referenceFormID":"0035D21C"},"geometry":{"type":"Point","coordinates":[85543,185304]}},{"type":"Feature","properties":{"referenceFormID":"0035D21C"},"geometry":{"type":"Point","coordinates":[84425,183455]}},{"type":"Feature","properties":{"referenceFormID":"0035D21C"},"geometry":{"type":"Point","coordinates":[116468,159903]}},{"type":"Feature","properties":{"referenceFormID":"0035D21C"},"geometry":{"type":"Point","coordinates":[118020,160407]}},{"type":"Feature","properties":{"referenceFormID":"0035D21C"},"geometry":{"type":"Point","coordinates":[115794,153470]}},{"type":"Feature","properties":{"referenceFormID":"0035D21C"},"geometry":{"type":"Point","coordinates":[113958,152648]}},{"type":"Feature","properties":{"referenceFormID":"0035D21C"},"geometry":{"type":"Point","coordinates":[101185,152272]}},{"type":"Feature","properties":{"referenceFormID":"0035D21C"},"geometry":{"type":"Point","coordinates":[119935,193084]}},{"type":"Feature","properties":{"referenceFormID":"0035D21C"},"geometry":{"type":"Point","coordinates":[105887,172052]}},{"type":"Feature","properties":{"referenceFormID":"0035D21C"},"geometry":{"type":"Point","coordinates":[104164,172107]}},{"type":"Feature","properties":{"referenceFormID":"0035D21C"},"geometry":{"type":"Point","coordinates":[105731,170759]}},{"type":"Feature","properties":{"referenceFormID":"0035D21C"},"geometry":{"type":"Point","coordinates":[109161,198999]}},{"type":"Feature","properties":{"referenceFormID":"0035D21C"},"geometry":{"type":"Point","coordinates":[29234,-170361]}},{"type":"Feature","properties":{"referenceFormID":"0035D21C"},"geometry":{"type":"Point","coordinates":[16453,-168590]}},{"type":"Feature","properties":{"referenceFormID":"0035D21C"},"geometry":{"type":"Point","coordinates":[30353,-156504]}},{"type":"Feature","properties":{"referenceFormID":"0035D21C"},"geometry":{"type":"Point","coordinates":[18217,-139217]}},{"type":"Feature","properties":{"referenceFormID":"0035D21C"},"geometry":{"type":"Point","coordinates":[4212,-158711]}},{"type":"Feature","properties":{"referenceFormID":"0035D21C"},"geometry":{"type":"Point","coordinates":[4233,-158683]}},{"type":"Feature","properties":{"referenceFormID":"0035D21C"},"geometry":{"type":"Point","coordinates":[62447,-174502]}},{"type":"Feature","properties":{"referenceFormID":"0035D21C"},"geometry":{"type":"Point","coordinates":[54906,-165480]}},{"type":"Feature","properties":{"referenceFormID":"0035D21C"},"geometry":{"type":"Point","coordinates":[39764,-166056]}},{"type":"Feature","properties":{"referenceFormID":"0035D21C"},"geometry":{"type":"Point","coordinates":[38388,-169880]}},{"type":"Feature","properties":{"referenceFormID":"0035D21C"},"geometry":{"type":"Point","coordinates":[33535,-179594]}},{"type":"Feature","properties":{"referenceFormID":"0035D21C"},"geometry":{"type":"Point","coordinates":[33021,-178487]}},{"type":"Feature","properties":{"referenceFormID":"0035D21C"},"geometry":{"type":"Point","coordinates":[47736,-145331]}},{"type":"Feature","properties":{"referenceFormID":"0035D21C"},"geometry":{"type":"Point","coordinates":[45586,-159830]}},{"type":"Feature","properties":{"referenceFormID":"0035D21C"},"geometry":{"type":"Point","coordinates":[42778,-153747]}},{"type":"Feature","properties":{"referenceFormID":"0035D21C"},"geometry":{"type":"Point","coordinates":[39427,-138915]}},{"type":"Feature","properties":{"referenceFormID":"0035D21C"},"geometry":{"type":"Point","coordinates":[37689,-158940]}},{"type":"Feature","properties":{"referenceFormID":"0035D21C"},"geometry":{"type":"Point","coordinates":[72650,-171754]}},{"type":"Feature","properties":{"referenceFormID":"0035D21C"},"geometry":{"type":"Point","coordinates":[92242,-143988]}},{"type":"Feature","properties":{"referenceFormID":"0035D21C"},"geometry":{"type":"Point","coordinates":[82796,-156248]}},{"type":"Feature","properties":{"referenceFormID":"0035D21C"},"geometry":{"type":"Point","coordinates":[83330,-157780]}},{"type":"Feature","properties":{"referenceFormID":"0035D21C"},"geometry":{"type":"Point","coordinates":[80903,-148224]}},{"type":"Feature","properties":{"referenceFormID":"0035D21C"},"geometry":{"type":"Point","coordinates":[106142,-173485]}},{"type":"Feature","properties":{"referenceFormID":"0035D21C"},"geometry":{"type":"Point","coordinates":[28130,-116727]}},{"type":"Feature","properties":{"referenceFormID":"0035D21C"},"geometry":{"type":"Point","coordinates":[5813,-115149]}},{"type":"Feature","properties":{"referenceFormID":"0035D21C"},"geometry":{"type":"Point","coordinates":[7333,-126476]}},{"type":"Feature","properties":{"referenceFormID":"0035D21C"},"geometry":{"type":"Point","coordinates":[30018,-75413]}},{"type":"Feature","properties":{"referenceFormID":"0035D21C"},"geometry":{"type":"Point","coordinates":[21103,-74582]}},{"type":"Feature","properties":{"referenceFormID":"0035D21C"},"geometry":{"type":"Point","coordinates":[11072,-72227]}},{"type":"Feature","properties":{"referenceFormID":"0035D21C"},"geometry":{"type":"Point","coordinates":[259,-89267]}},{"type":"Feature","properties":{"referenceFormID":"0035D21C"},"geometry":{"type":"Point","coordinates":[30145,-42443]}},{"type":"Feature","properties":{"referenceFormID":"0035D21C"},"geometry":{"type":"Point","coordinates":[32023,-56445]}},{"type":"Feature","properties":{"referenceFormID":"0035D21C"},"geometry":{"type":"Point","coordinates":[32095,-56442]}},{"type":"Feature","properties":{"referenceFormID":"0035D21C"},"geometry":{"type":"Point","coordinates":[27336,-38768]}},{"type":"Feature","properties":{"referenceFormID":"0035D21C"},"geometry":{"type":"Point","coordinates":[26892,-52371]}},{"type":"Feature","properties":{"referenceFormID":"0035D21C"},"geometry":{"type":"Point","coordinates":[24176,-45636]}},{"type":"Feature","properties":{"referenceFormID":"0035D21C"},"geometry":{"type":"Point","coordinates":[19574,-35299]}},{"type":"Feature","properties":{"referenceFormID":"0035D21C"},"geometry":{"type":"Point","coordinates":[19585,-35281]}},{"type":"Feature","properties":{"referenceFormID":"0035D21C"},"geometry":{"type":"Point","coordinates":[18507,-57506]}},{"type":"Feature","properties":{"referenceFormID":"0035D21C"},"geometry":{"type":"Point","coordinates":[19404,-64182]}},{"type":"Feature","properties":{"referenceFormID":"0035D21C"},"geometry":{"type":"Point","coordinates":[12877,-37701]}},{"type":"Feature","properties":{"referenceFormID":"0035D21C"},"geometry":{"type":"Point","coordinates":[14058,-53569]}},{"type":"Feature","properties":{"referenceFormID":"0035D21C"},"geometry":{"type":"Point","coordinates":[13571,-65076]}},{"type":"Feature","properties":{"referenceFormID":"0035D21C"},"geometry":{"type":"Point","coordinates":[11362,-35219]}},{"type":"Feature","properties":{"referenceFormID":"0035D21C"},"geometry":{"type":"Point","coordinates":[11360,-35190]}},{"type":"Feature","properties":{"referenceFormID":"0035D21C"},"geometry":{"type":"Point","coordinates":[8873,-62179]}},{"type":"Feature","properties":{"referenceFormID":"0035D21C"},"geometry":{"type":"Point","coordinates":[5708,-33633]}},{"type":"Feature","properties":{"referenceFormID":"0035D21C"},"geometry":{"type":"Point","coordinates":[5694,-33693]}},{"type":"Feature","properties":{"referenceFormID":"0035D21C"},"geometry":{"type":"Point","coordinates":[5713,-33653]}},{"type":"Feature","properties":{"referenceFormID":"0035D21C"},"geometry":{"type":"Point","coordinates":[5081,-62527]}},{"type":"Feature","properties":{"referenceFormID":"0035D21C"},"geometry":{"type":"Point","coordinates":[29090,-7885]}},{"type":"Feature","properties":{"referenceFormID":"0035D21C"},"geometry":{"type":"Point","coordinates":[31786,-25626]}},{"type":"Feature","properties":{"referenceFormID":"0035D21C"},"geometry":{"type":"Point","coordinates":[28075,-31003]}},{"type":"Feature","properties":{"referenceFormID":"0035D21C"},"geometry":{"type":"Point","coordinates":[24394,-25474]}},{"type":"Feature","properties":{"referenceFormID":"0035D21C"},"geometry":{"type":"Point","coordinates":[24449,-25287]}},{"type":"Feature","properties":{"referenceFormID":"0035D21C"},"geometry":{"type":"Point","coordinates":[24325,-30184]}},{"type":"Feature","properties":{"referenceFormID":"0035D21C"},"geometry":{"type":"Point","coordinates":[24416,-29097]}},{"type":"Feature","properties":{"referenceFormID":"0035D21C"},"geometry":{"type":"Point","coordinates":[16289,-23733]}},{"type":"Feature","properties":{"referenceFormID":"0035D21C"},"geometry":{"type":"Point","coordinates":[15733,-26578]}},{"type":"Feature","properties":{"referenceFormID":"0035D21C"},"geometry":{"type":"Point","coordinates":[12584,-31584]}},{"type":"Feature","properties":{"referenceFormID":"0035D21C"},"geometry":{"type":"Point","coordinates":[10776,-12837]}},{"type":"Feature","properties":{"referenceFormID":"0035D21C"},"geometry":{"type":"Point","coordinates":[11513,-19839]}},{"type":"Feature","properties":{"referenceFormID":"0035D21C"},"geometry":{"type":"Point","coordinates":[5328,-3667]}},{"type":"Feature","properties":{"referenceFormID":"0035D21C"},"geometry":{"type":"Point","coordinates":[5309,-3725]}},{"type":"Feature","properties":{"referenceFormID":"0035D21C"},"geometry":{"type":"Point","coordinates":[5244,-3694]}},{"type":"Feature","properties":{"referenceFormID":"0035D21C"},"geometry":{"type":"Point","coordinates":[4984,-9075]}},{"type":"Feature","properties":{"referenceFormID":"0035D21C"},"geometry":{"type":"Point","coordinates":[4994,-21185]}},{"type":"Feature","properties":{"referenceFormID":"0035D21C"},"geometry":{"type":"Point","coordinates":[4094,-23179]}},{"type":"Feature","properties":{"referenceFormID":"0035D21C"},"geometry":{"type":"Point","coordinates":[4029,-23199]}},{"type":"Feature","properties":{"referenceFormID":"0035D21C"},"geometry":{"type":"Point","coordinates":[4003,-23155]}},{"type":"Feature","properties":{"referenceFormID":"0035D21C"},"geometry":{"type":"Point","coordinates":[56609,-104752]}},{"type":"Feature","properties":{"referenceFormID":"0035D21C"},"geometry":{"type":"Point","coordinates":[56013,-120845]}},{"type":"Feature","properties":{"referenceFormID":"0035D21C"},"geometry":{"type":"Point","coordinates":[52403,-90874]}},{"type":"Feature","properties":{"referenceFormID":"0035D21C"},"geometry":{"type":"Point","coordinates":[37207,-72544]}},{"type":"Feature","properties":{"referenceFormID":"0035D21C"},"geometry":{"type":"Point","coordinates":[38328,-85448]}},{"type":"Feature","properties":{"referenceFormID":"0035D21C"},"geometry":{"type":"Point","coordinates":[32780,-76179]}},{"type":"Feature","properties":{"referenceFormID":"0035D21C"},"geometry":{"type":"Point","coordinates":[32837,-76155]}},{"type":"Feature","properties":{"referenceFormID":"0035D21C"},"geometry":{"type":"Point","coordinates":[33607,-96705]}},{"type":"Feature","properties":{"referenceFormID":"0035D21C"},"geometry":{"type":"Point","coordinates":[57103,-60480]}},{"type":"Feature","properties":{"referenceFormID":"0035D21C"},"geometry":{"type":"Point","coordinates":[53132,-47294]}},{"type":"Feature","properties":{"referenceFormID":"0035D21C"},"geometry":{"type":"Point","coordinates":[45339,-44691]}},{"type":"Feature","properties":{"referenceFormID":"0035D21C"},"geometry":{"type":"Point","coordinates":[46991,-64866]}},{"type":"Feature","properties":{"referenceFormID":"0035D21C"},"geometry":{"type":"Point","coordinates":[46933,-64770]}},{"type":"Feature","properties":{"referenceFormID":"0035D21C"},"geometry":{"type":"Point","coordinates":[46886,-64837]}},{"type":"Feature","properties":{"referenceFormID":"0035D21C"},"geometry":{"type":"Point","coordinates":[41208,-38931]}},{"type":"Feature","properties":{"referenceFormID":"0035D21C"},"geometry":{"type":"Point","coordinates":[43539,-40216]}},{"type":"Feature","properties":{"referenceFormID":"0035D21C"},"geometry":{"type":"Point","coordinates":[43484,-40143]}},{"type":"Feature","properties":{"referenceFormID":"0035D21C"},"geometry":{"type":"Point","coordinates":[43396,-40190]}},{"type":"Feature","properties":{"referenceFormID":"0035D21C"},"geometry":{"type":"Point","coordinates":[42771,-45724]}},{"type":"Feature","properties":{"referenceFormID":"0035D21C"},"geometry":{"type":"Point","coordinates":[41854,-50477]}},{"type":"Feature","properties":{"referenceFormID":"0035D21C"},"geometry":{"type":"Point","coordinates":[41937,-50472]}},{"type":"Feature","properties":{"referenceFormID":"0035D21C"},"geometry":{"type":"Point","coordinates":[39250,-46037]}},{"type":"Feature","properties":{"referenceFormID":"0035D21C"},"geometry":{"type":"Point","coordinates":[39181,-46050]}},{"type":"Feature","properties":{"referenceFormID":"0035D21C"},"geometry":{"type":"Point","coordinates":[36219,-34588]}},{"type":"Feature","properties":{"referenceFormID":"0035D21C"},"geometry":{"type":"Point","coordinates":[36198,-34557]}},{"type":"Feature","properties":{"referenceFormID":"0035D21C"},"geometry":{"type":"Point","coordinates":[36254,-37581]}},{"type":"Feature","properties":{"referenceFormID":"0035D21C"},"geometry":{"type":"Point","coordinates":[33098,-39920]}},{"type":"Feature","properties":{"referenceFormID":"0035D21C"},"geometry":{"type":"Point","coordinates":[33062,-42550]}},{"type":"Feature","properties":{"referenceFormID":"0035D21C"},"geometry":{"type":"Point","coordinates":[36600,-43546]}},{"type":"Feature","properties":{"referenceFormID":"0035D21C"},"geometry":{"type":"Point","coordinates":[33476,-48460]}},{"type":"Feature","properties":{"referenceFormID":"0035D21C"},"geometry":{"type":"Point","coordinates":[33456,-48432]}},{"type":"Feature","properties":{"referenceFormID":"0035D21C"},"geometry":{"type":"Point","coordinates":[41658,-13569]}},{"type":"Feature","properties":{"referenceFormID":"0035D21C"},"geometry":{"type":"Point","coordinates":[41723,-13594]}},{"type":"Feature","properties":{"referenceFormID":"0035D21C"},"geometry":{"type":"Point","coordinates":[45005,-25247]}},{"type":"Feature","properties":{"referenceFormID":"0035D21C"},"geometry":{"type":"Point","coordinates":[41543,-31138]}},{"type":"Feature","properties":{"referenceFormID":"0035D21C"},"geometry":{"type":"Point","coordinates":[41578,-31088]}},{"type":"Feature","properties":{"referenceFormID":"0035D21C"},"geometry":{"type":"Point","coordinates":[40365,-25896]}},{"type":"Feature","properties":{"referenceFormID":"0035D21C"},"geometry":{"type":"Point","coordinates":[40338,-25872]}},{"type":"Feature","properties":{"referenceFormID":"0035D21C"},"geometry":{"type":"Point","coordinates":[37259,-31039]}},{"type":"Feature","properties":{"referenceFormID":"0035D21C"},"geometry":{"type":"Point","coordinates":[36269,-1266]}},{"type":"Feature","properties":{"referenceFormID":"0035D21C"},"geometry":{"type":"Point","coordinates":[36212,-11230]}},{"type":"Feature","properties":{"referenceFormID":"0035D21C"},"geometry":{"type":"Point","coordinates":[36225,-11187]}},{"type":"Feature","properties":{"referenceFormID":"0035D21C"},"geometry":{"type":"Point","coordinates":[33088,-30669]}},{"type":"Feature","properties":{"referenceFormID":"0035D21C"},"geometry":{"type":"Point","coordinates":[33144,-30622]}},{"type":"Feature","properties":{"referenceFormID":"0035D21C"},"geometry":{"type":"Point","coordinates":[95800,-118618]}},{"type":"Feature","properties":{"referenceFormID":"0035D21C"},"geometry":{"type":"Point","coordinates":[75299,-107644]}},{"type":"Feature","properties":{"referenceFormID":"0035D21C"},"geometry":{"type":"Point","coordinates":[75843,-125073]}},{"type":"Feature","properties":{"referenceFormID":"0035D21C"},"geometry":{"type":"Point","coordinates":[80559,-67762]}},{"type":"Feature","properties":{"referenceFormID":"0035D21C"},"geometry":{"type":"Point","coordinates":[79241,-86553]}},{"type":"Feature","properties":{"referenceFormID":"0035D21C"},"geometry":{"type":"Point","coordinates":[70629,-88459]}},{"type":"Feature","properties":{"referenceFormID":"0035D21C"},"geometry":{"type":"Point","coordinates":[97137,-45648]}},{"type":"Feature","properties":{"referenceFormID":"0035D21C"},"geometry":{"type":"Point","coordinates":[84309,-64750]}},{"type":"Feature","properties":{"referenceFormID":"0035D21C"},"geometry":{"type":"Point","coordinates":[79081,-38826]}},{"type":"Feature","properties":{"referenceFormID":"0035D21C"},"geometry":{"type":"Point","coordinates":[94902,-10385]}},{"type":"Feature","properties":{"referenceFormID":"0035D21C"},"geometry":{"type":"Point","coordinates":[92437,-23372]}},{"type":"Feature","properties":{"referenceFormID":"0035D21C"},"geometry":{"type":"Point","coordinates":[80466,-16984]}},{"type":"Feature","properties":{"referenceFormID":"0035D21C"},"geometry":{"type":"Point","coordinates":[78952,-20867]}},{"type":"Feature","properties":{"referenceFormID":"0035D21C"},"geometry":{"type":"Point","coordinates":[72630,-9453]}},{"type":"Feature","properties":{"referenceFormID":"0035D21C"},"geometry":{"type":"Point","coordinates":[66282,-30156]}},{"type":"Feature","properties":{"referenceFormID":"0035D21C"},"geometry":{"type":"Point","coordinates":[99834,-70691]}},{"type":"Feature","properties":{"referenceFormID":"0035D21C"},"geometry":{"type":"Point","coordinates":[128537,-41024]}},{"type":"Feature","properties":{"referenceFormID":"0035D21C"},"geometry":{"type":"Point","coordinates":[124309,-51339]}},{"type":"Feature","properties":{"referenceFormID":"0035D21C"},"geometry":{"type":"Point","coordinates":[109779,-44436]}},{"type":"Feature","properties":{"referenceFormID":"0035D21C"},"geometry":{"type":"Point","coordinates":[102703,-36187]}},{"type":"Feature","properties":{"referenceFormID":"0035D21C"},"geometry":{"type":"Point","coordinates":[125181,-26275]}},{"type":"Feature","properties":{"referenceFormID":"0035D21C"},"geometry":{"type":"Point","coordinates":[112871,-21489]}},{"type":"Feature","properties":{"referenceFormID":"0035D21C"},"geometry":{"type":"Point","coordinates":[109390,-1024]}},{"type":"Feature","properties":{"referenceFormID":"0035D21C"},"geometry":{"type":"Point","coordinates":[151302,140657]}},{"type":"Feature","properties":{"referenceFormID":"0035D21C"},"geometry":{"type":"Point","coordinates":[153648,193906]}},{"type":"Feature","properties":{"referenceFormID":"0035D21C"},"geometry":{"type":"Point","coordinates":[153673,193988]}},{"type":"Feature","properties":{"referenceFormID":"0035D21C"},"geometry":{"type":"Point","coordinates":[152181,164164]}},{"type":"Feature","properties":{"referenceFormID":"0035D21C"},"geometry":{"type":"Point","coordinates":[152146,164082]}},{"type":"Feature","properties":{"referenceFormID":"0035D21C"},"geometry":{"type":"Point","coordinates":[152071,164196]}},{"type":"Feature","properties":{"referenceFormID":"0035D21C"},"geometry":{"type":"Point","coordinates":[141666,187450]}},{"type":"Feature","properties":{"referenceFormID":"0035D21C"},"geometry":{"type":"Point","coordinates":[141701,187564]}},{"type":"Feature","properties":{"referenceFormID":"0035D21C"},"geometry":{"type":"Point","coordinates":[132584,186883]}},{"type":"Feature","properties":{"referenceFormID":"0035D21C"},"geometry":{"type":"Point","coordinates":[132625,186956]}},{"type":"Feature","properties":{"referenceFormID":"0035D21C"},"geometry":{"type":"Point","coordinates":[181265,193001]}},{"type":"Feature","properties":{"referenceFormID":"0035D21C"},"geometry":{"type":"Point","coordinates":[-165246,90030]}},{"type":"Feature","properties":{"referenceFormID":"0035D21C"},"geometry":{"type":"Point","coordinates":[-147983,80606]}},{"type":"Feature","properties":{"referenceFormID":"0035D21C"},"geometry":{"type":"Point","coordinates":[-151484,75972]}},{"type":"Feature","properties":{"referenceFormID":"0035D21C"},"geometry":{"type":"Point","coordinates":[-151711,72256]}},{"type":"Feature","properties":{"referenceFormID":"0035D21C"},"geometry":{"type":"Point","coordinates":[-161095,72417]}},{"type":"Feature","properties":{"referenceFormID":"0035D21C"},"geometry":{"type":"Point","coordinates":[-1,3]}},{"type":"Feature","properties":{"referenceFormID":"0035D21C"},"geometry":{"type":"Point","coordinates":[-58940,196355]}},{"type":"Feature","properties":{"referenceFormID":"0035D21C"},"geometry":{"type":"Point","coordinates":[-53425,205772]}},{"type":"Feature","properties":{"referenceFormID":"0035D21C"},"geometry":{"type":"Point","coordinates":[-53410,205800]}},{"type":"Feature","properties":{"referenceFormID":"0035D21C"},"geometry":{"type":"Point","coordinates":[-105160,-169003]}},{"type":"Feature","properties":{"referenceFormID":"0035D21C"},"geometry":{"type":"Point","coordinates":[-103338,-177241]}},{"type":"Feature","properties":{"referenceFormID":"0035D21C"},"geometry":{"type":"Point","coordinates":[-102040,-161144]}},{"type":"Feature","properties":{"referenceFormID":"0035D21C"},"geometry":{"type":"Point","coordinates":[-107526,-162960]}},{"type":"Feature","properties":{"referenceFormID":"0035D21C"},"geometry":{"type":"Point","coordinates":[-82468,-170611]}},{"type":"Feature","properties":{"referenceFormID":"0035D21C"},"geometry":{"type":"Point","coordinates":[-91419,-165539]}},{"type":"Feature","properties":{"referenceFormID":"0035D21C"},"geometry":{"type":"Point","coordinates":[-78466,-160925]}},{"type":"Feature","properties":{"referenceFormID":"0035D21C"},"geometry":{"type":"Point","coordinates":[-38033,-186200]}},{"type":"Feature","properties":{"referenceFormID":"0035D21C"},"geometry":{"type":"Point","coordinates":[-37930,-187145]}},{"type":"Feature","properties":{"referenceFormID":"0035D21C"},"geometry":{"type":"Point","coordinates":[-44020,-186325]}},{"type":"Feature","properties":{"referenceFormID":"0035D21C"},"geometry":{"type":"Point","coordinates":[-42558,-193341]}},{"type":"Feature","properties":{"referenceFormID":"0035D21C"},"geometry":{"type":"Point","coordinates":[-45129,-167426]}},{"type":"Feature","properties":{"referenceFormID":"0035D21C"},"geometry":{"type":"Point","coordinates":[-46070,-188244]}},{"type":"Feature","properties":{"referenceFormID":"0035D21C"},"geometry":{"type":"Point","coordinates":[-48093,-193352]}},{"type":"Feature","properties":{"referenceFormID":"0035D21C"},"geometry":{"type":"Point","coordinates":[-46303,-195942]}},{"type":"Feature","properties":{"referenceFormID":"0035D21C"},"geometry":{"type":"Point","coordinates":[-46415,-195944]}},{"type":"Feature","properties":{"referenceFormID":"0035D21C"},"geometry":{"type":"Point","coordinates":[-41552,-150034]}},{"type":"Feature","properties":{"referenceFormID":"0035D21C"},"geometry":{"type":"Point","coordinates":[-43055,-149052]}},{"type":"Feature","properties":{"referenceFormID":"0035D21C"},"geometry":{"type":"Point","coordinates":[-45042,-149042]}},{"type":"Feature","properties":{"referenceFormID":"0035D21C"},"geometry":{"type":"Point","coordinates":[-21480,-147683]}},{"type":"Feature","properties":{"referenceFormID":"0035D21C"},"geometry":{"type":"Point","coordinates":[-33645,-126854]}},{"type":"Feature","properties":{"referenceFormID":"0035D21C"},"geometry":{"type":"Point","coordinates":[-34679,-126833]}},{"type":"Feature","properties":{"referenceFormID":"0035D21C"},"geometry":{"type":"Point","coordinates":[-39178,-129988]}},{"type":"Feature","properties":{"referenceFormID":"0035D21C"},"geometry":{"type":"Point","coordinates":[-4496,-108822]}},{"type":"Feature","properties":{"referenceFormID":"0035D21C"},"geometry":{"type":"Point","coordinates":[-18883,-117922]}},{"type":"Feature","properties":{"referenceFormID":"0035D21C"},"geometry":{"type":"Point","coordinates":[-30652,-87932]}},{"type":"Feature","properties":{"referenceFormID":"0035D21C"},"geometry":{"type":"Point","coordinates":[-19739,-46880]}}]}
