{"type":"FeatureCollection","features":[{"type":"Feature","properties":{"referenceFormID":"0052BE2E"},"geometry":{"type":"Point","coordinates":[-23108,197153]}},{"type":"Feature","properties":{"referenceFormID":"0052BE2E"},"geometry":{"type":"Point","coordinates":[52329,78683]}},{"type":"Feature","properties":{"referenceFormID":"0052BE2E"},"geometry":{"type":"Point","coordinates":[99118,-25556]}},{"type":"Feature","properties":{"referenceFormID":"0052BE2E"},"geometry":{"type":"Point","coordinates":[-153692,108037]}},{"type":"Feature","properties":{"referenceFormID":"0052BE2E"},"geometry":{"type":"Point","coordinates":[-84141,59477]}},{"type":"Feature","properties":{"referenceFormID":"0052BE2E"},"geometry":{"type":"Point","coordinates":[-11798,102283]}},{"type":"Feature","properties":{"referenceFormID":"0052BE2E"},"geometry":{"type":"Point","coordinates":[-43881,-15209]}}]}
