{"type":"FeatureCollection","features":[{"type":"Feature","properties":{"referenceFormID":"000070B4"},"geometry":{"type":"Point","coordinates":[119373,6930]}},{"type":"Feature","properties":{"referenceFormID":"000070B4"},"geometry":{"type":"Point","coordinates":[117562,6030]}},{"type":"Feature","properties":{"referenceFormID":"000070B4"},"geometry":{"type":"Point","coordinates":[128729,36231]}},{"type":"Feature","properties":{"referenceFormID":"000070B4"},"geometry":{"type":"Point","coordinates":[106378,98101]}},{"type":"Feature","properties":{"referenceFormID":"000070B4"},"geometry":{"type":"Point","coordinates":[103268,93471]}},{"type":"Feature","properties":{"referenceFormID":"000070B4"},"geometry":{"type":"Point","coordinates":[20383,133787]}},{"type":"Feature","properties":{"referenceFormID":"000070B4"},"geometry":{"type":"Point","coordinates":[11821,131740]}},{"type":"Feature","properties":{"referenceFormID":"000070B4"},"geometry":{"type":"Point","coordinates":[1871,171000]}},{"type":"Feature","properties":{"referenceFormID":"000070B4"},"geometry":{"type":"Point","coordinates":[43265,137062]}},{"type":"Feature","properties":{"referenceFormID":"000070B4"},"geometry":{"type":"Point","coordinates":[43232,137077]}},{"type":"Feature","properties":{"referenceFormID":"000070B4"},"geometry":{"type":"Point","coordinates":[39211,172798]}},{"type":"Feature","properties":{"referenceFormID":"000070B4"},"geometry":{"type":"Point","coordinates":[88502,-139113]}},{"type":"Feature","properties":{"referenceFormID":"000070B4"},"geometry":{"type":"Point","coordinates":[10595,-130926]}},{"type":"Feature","properties":{"referenceFormID":"000070B4"},"geometry":{"type":"Point","coordinates":[7629,-98946]}},{"type":"Feature","properties":{"referenceFormID":"000070B4"},"geometry":{"type":"Point","coordinates":[13095,-34650]}},{"type":"Feature","properties":{"referenceFormID":"000070B4"},"geometry":{"type":"Point","coordinates":[55530,-69138]}},{"type":"Feature","properties":{"referenceFormID":"000070B4"},"geometry":{"type":"Point","coordinates":[60513,-17687]}},{"type":"Feature","properties":{"referenceFormID":"000070B4"},"geometry":{"type":"Point","coordinates":[33979,-5285]}},{"type":"Feature","properties":{"referenceFormID":"000070B4"},"geometry":{"type":"Point","coordinates":[151246,75069]}},{"type":"Feature","properties":{"referenceFormID":"000070B4"},"geometry":{"type":"Point","coordinates":[181994,2592]}},{"type":"Feature","properties":{"referenceFormID":"000070B4"},"geometry":{"type":"Point","coordinates":[164097,6289]}},{"type":"Feature","properties":{"referenceFormID":"000070B4"},"geometry":{"type":"Point","coordinates":[172899,63122]}},{"type":"Feature","properties":{"referenceFormID":"000070B4"},"geometry":{"type":"Point","coordinates":[138267,147354]}},{"type":"Feature","properties":{"referenceFormID":"000070B4"},"geometry":{"type":"Point","coordinates":[145116,186927]}},{"type":"Feature","properties":{"referenceFormID":"000070B4"},"geometry":{"type":"Point","coordinates":[178643,-146920]}},{"type":"Feature","properties":{"referenceFormID":"000070B4"},"geometry":{"type":"Point","coordinates":[173093,-146159]}},{"type":"Feature","properties":{"referenceFormID":"000070B4"},"geometry":{"type":"Point","coordinates":[159910,-37945]}},{"type":"Feature","properties":{"referenceFormID":"000070B4"},"geometry":{"type":"Point","coordinates":[161366,-40658]}},{"type":"Feature","properties":{"referenceFormID":"000070B4"},"geometry":{"type":"Point","coordinates":[161320,-40948]}},{"type":"Feature","properties":{"referenceFormID":"000070B4"},"geometry":{"type":"Point","coordinates":[160640,-5794]}},{"type":"Feature","properties":{"referenceFormID":"000070B4"},"geometry":{"type":"Point","coordinates":[158431,-2691]}},{"type":"Feature","properties":{"referenceFormID":"000070B4"},"geometry":{"type":"Point","coordinates":[183531,-98854]}},{"type":"Feature","properties":{"referenceFormID":"000070B4"},"geometry":{"type":"Point","coordinates":[196362,-67800]}},{"type":"Feature","properties":{"referenceFormID":"000070B4"},"geometry":{"type":"Point","coordinates":[189967,-96645]}},{"type":"Feature","properties":{"referenceFormID":"000070B4"},"geometry":{"type":"Point","coordinates":[190280,-38781]}},{"type":"Feature","properties":{"referenceFormID":"000070B4"},"geometry":{"type":"Point","coordinates":[182059,-60636]}},{"type":"Feature","properties":{"referenceFormID":"000070B4"},"geometry":{"type":"Point","coordinates":[182201,-61670]}},{"type":"Feature","properties":{"referenceFormID":"000070B4"},"geometry":{"type":"Point","coordinates":[-177676,73760]}},{"type":"Feature","properties":{"referenceFormID":"000070B4"},"geometry":{"type":"Point","coordinates":[-145304,193200]}},{"type":"Feature","properties":{"referenceFormID":"000070B4"},"geometry":{"type":"Point","coordinates":[-149024,165023]}},{"type":"Feature","properties":{"referenceFormID":"000070B4"},"geometry":{"type":"Point","coordinates":[-150424,164460]}},{"type":"Feature","properties":{"referenceFormID":"000070B4"},"geometry":{"type":"Point","coordinates":[-179294,-80863]}},{"type":"Feature","properties":{"referenceFormID":"000070B4"},"geometry":{"type":"Point","coordinates":[-179712,-82109]}},{"type":"Feature","properties":{"referenceFormID":"000070B4"},"geometry":{"type":"Point","coordinates":[-177877,-81926]}},{"type":"Feature","properties":{"referenceFormID":"000070B4"},"geometry":{"type":"Point","coordinates":[-178534,-82625]}},{"type":"Feature","properties":{"referenceFormID":"000070B4"},"geometry":{"type":"Point","coordinates":[-184243,-76424]}},{"type":"Feature","properties":{"referenceFormID":"000070B4"},"geometry":{"type":"Point","coordinates":[-172875,-42171]}},{"type":"Feature","properties":{"referenceFormID":"000070B4"},"geometry":{"type":"Point","coordinates":[-172883,-42187]}},{"type":"Feature","properties":{"referenceFormID":"000070B4"},"geometry":{"type":"Point","coordinates":[-188527,-31155]}},{"type":"Feature","properties":{"referenceFormID":"000070B4"},"geometry":{"type":"Point","coordinates":[-135199,-126490]}},{"type":"Feature","properties":{"referenceFormID":"000070B4"},"geometry":{"type":"Point","coordinates":[-163374,-93782]}},{"type":"Feature","properties":{"referenceFormID":"000070B4"},"geometry":{"type":"Point","coordinates":[-145490,-61212]}},{"type":"Feature","properties":{"referenceFormID":"000070B4"},"geometry":{"type":"Point","coordinates":[-161348,-7195]}},{"type":"Feature","properties":{"referenceFormID":"000070B4"},"geometry":{"type":"Point","coordinates":[-161329,-7164]}},{"type":"Feature","properties":{"referenceFormID":"000070B4"},"geometry":{"type":"Point","coordinates":[-161341,-7178]}},{"type":"Feature","properties":{"referenceFormID":"000070B4"},"geometry":{"type":"Point","coordinates":[-161520,-7027]}},{"type":"Feature","properties":{"referenceFormID":"000070B4"},"geometry":{"type":"Point","coordinates":[-106089,28635]}},{"type":"Feature","properties":{"referenceFormID":"000070B4"},"geometry":{"type":"Point","coordinates":[-35306,35948]}},{"type":"Feature","properties":{"referenceFormID":"000070B4"},"geometry":{"type":"Point","coordinates":[-50124,63888]}},{"type":"Feature","properties":{"referenceFormID":"000070B4"},"geometry":{"type":"Point","coordinates":[-55255,111285]}},{"type":"Feature","properties":{"referenceFormID":"000070B4"},"geometry":{"type":"Point","coordinates":[-30311,8983]}},{"type":"Feature","properties":{"referenceFormID":"000070B4"},"geometry":{"type":"Point","coordinates":[-22991,59623]}},{"type":"Feature","properties":{"referenceFormID":"000070B4"},"geometry":{"type":"Point","coordinates":[-22108,48137]}},{"type":"Feature","properties":{"referenceFormID":"000070B4"},"geometry":{"type":"Point","coordinates":[-22339,48444]}},{"type":"Feature","properties":{"referenceFormID":"000070B4"},"geometry":{"type":"Point","coordinates":[-1700,71132]}},{"type":"Feature","properties":{"referenceFormID":"000070B4"},"geometry":{"type":"Point","coordinates":[-31286,88608]}},{"type":"Feature","properties":{"referenceFormID":"000070B4"},"geometry":{"type":"Point","coordinates":[-69463,157604]}},{"type":"Feature","properties":{"referenceFormID":"000070B4"},"geometry":{"type":"Point","coordinates":[-18071,173219]}},{"type":"Feature","properties":{"referenceFormID":"000070B4"},"geometry":{"type":"Point","coordinates":[-115177,-168135]}},{"type":"Feature","properties":{"referenceFormID":"000070B4"},"geometry":{"type":"Point","coordinates":[-115727,-167968]}},{"type":"Feature","properties":{"referenceFormID":"000070B4"},"geometry":{"type":"Point","coordinates":[-2880,-178592]}},{"type":"Feature","properties":{"referenceFormID":"000070B4"},"geometry":{"type":"Point","coordinates":[-14738,-155790]}},{"type":"Feature","properties":{"referenceFormID":"000070B4"},"geometry":{"type":"Point","coordinates":[-117772,-114465]}},{"type":"Feature","properties":{"referenceFormID":"000070B4"},"geometry":{"type":"Point","coordinates":[-106586,-85958]}},{"type":"Feature","properties":{"referenceFormID":"000070B4"},"geometry":{"type":"Point","coordinates":[-106868,-88886]}},{"type":"Feature","properties":{"referenceFormID":"000070B4"},"geometry":{"type":"Point","coordinates":[-93056,-29870]}},{"type":"Feature","properties":{"referenceFormID":"000070B4"},"geometry":{"type":"Point","coordinates":[-47299,-114602]}},{"type":"Feature","properties":{"referenceFormID":"000070B4"},"geometry":{"type":"Point","coordinates":[-64767,-110161]}},{"type":"Feature","properties":{"referenceFormID":"000070B4"},"geometry":{"type":"Point","coordinates":[-65231,-120810]}},{"type":"Feature","properties":{"referenceFormID":"000070B4"},"geometry":{"type":"Point","coordinates":[-65218,-120811]}},{"type":"Feature","properties":{"referenceFormID":"000070B4"},"geometry":{"type":"Point","coordinates":[-65225,-120818]}},{"type":"Feature","properties":{"referenceFormID":"000070B4"},"geometry":{"type":"Point","coordinates":[-64831,-121045]}},{"type":"Feature","properties":{"referenceFormID":"000070B4"},"geometry":{"type":"Point","coordinates":[-50551,-46004]}},{"type":"Feature","properties":{"referenceFormID":"000070B4"},"geometry":{"type":"Point","coordinates":[-56958,-60002]}},{"type":"Feature","properties":{"referenceFormID":"000070B4"},"geometry":{"type":"Point","coordinates":[-56634,-61425]}},{"type":"Feature","properties":{"referenceFormID":"000070B4"},"geometry":{"type":"Point","coordinates":[-57370,-38027]}},{"type":"Feature","properties":{"referenceFormID":"000070B4"},"geometry":{"type":"Point","coordinates":[-58828,-39572]}},{"type":"Feature","properties":{"referenceFormID":"000070B4"},"geometry":{"type":"Point","coordinates":[-14381,-107614]}},{"type":"Feature","properties":{"referenceFormID":"000070B4"},"geometry":{"type":"Point","coordinates":[-27575,-121325]}},{"type":"Feature","properties":{"referenceFormID":"000070B4"},"geometry":{"type":"Point","coordinates":[-15766,-44789]}}]}
