{"type":"FeatureCollection","features":[{"type":"Feature","properties":{"referenceFormID":"0011109F"},"geometry":{"type":"Point","coordinates":[22806,41014]}},{"type":"Feature","properties":{"referenceFormID":"0011109F"},"geometry":{"type":"Point","coordinates":[23683,41223]}},{"type":"Feature","properties":{"referenceFormID":"0011109F"},"geometry":{"type":"Point","coordinates":[23296,41503]}},{"type":"Feature","properties":{"referenceFormID":"0011109F"},"geometry":{"type":"Point","coordinates":[69373,25649]}},{"type":"Feature","properties":{"referenceFormID":"0011109F"},"geometry":{"type":"Point","coordinates":[85808,50219]}},{"type":"Feature","properties":{"referenceFormID":"0011109F"},"geometry":{"type":"Point","coordinates":[70393,77268]}},{"type":"Feature","properties":{"referenceFormID":"0011109F"},"geometry":{"type":"Point","coordinates":[117670,7778]}},{"type":"Feature","properties":{"referenceFormID":"0011109F"},"geometry":{"type":"Point","coordinates":[115861,39266]}},{"type":"Feature","properties":{"referenceFormID":"0011109F"},"geometry":{"type":"Point","coordinates":[97167,181933]}},{"type":"Feature","properties":{"referenceFormID":"0011109F"},"geometry":{"type":"Point","coordinates":[113793,192214]}},{"type":"Feature","properties":{"referenceFormID":"0011109F"},"geometry":{"type":"Point","coordinates":[12888,-33556]}},{"type":"Feature","properties":{"referenceFormID":"0011109F"},"geometry":{"type":"Point","coordinates":[51471,-123203]}},{"type":"Feature","properties":{"referenceFormID":"0011109F"},"geometry":{"type":"Point","coordinates":[45436,-39645]}},{"type":"Feature","properties":{"referenceFormID":"0011109F"},"geometry":{"type":"Point","coordinates":[129333,-65758]}},{"type":"Feature","properties":{"referenceFormID":"0011109F"},"geometry":{"type":"Point","coordinates":[162508,45791]}},{"type":"Feature","properties":{"referenceFormID":"0011109F"},"geometry":{"type":"Point","coordinates":[131654,-63667]}},{"type":"Feature","properties":{"referenceFormID":"0011109F"},"geometry":{"type":"Point","coordinates":[162692,-27519]}},{"type":"Feature","properties":{"referenceFormID":"0011109F"},"geometry":{"type":"Point","coordinates":[-150829,51278]}},{"type":"Feature","properties":{"referenceFormID":"0011109F"},"geometry":{"type":"Point","coordinates":[-174016,171546]}},{"type":"Feature","properties":{"referenceFormID":"0011109F"},"geometry":{"type":"Point","coordinates":[-148494,165660]}},{"type":"Feature","properties":{"referenceFormID":"0011109F"},"geometry":{"type":"Point","coordinates":[-174951,-75871]}},{"type":"Feature","properties":{"referenceFormID":"0011109F"},"geometry":{"type":"Point","coordinates":[-177787,-82603]}},{"type":"Feature","properties":{"referenceFormID":"0011109F"},"geometry":{"type":"Point","coordinates":[-154734,-28967]}},{"type":"Feature","properties":{"referenceFormID":"0011109F"},"geometry":{"type":"Point","coordinates":[-111146,13080]}},{"type":"Feature","properties":{"referenceFormID":"0011109F"},"geometry":{"type":"Point","coordinates":[-116429,89310]}},{"type":"Feature","properties":{"referenceFormID":"0011109F"},"geometry":{"type":"Point","coordinates":[-99479,101448]}},{"type":"Feature","properties":{"referenceFormID":"0011109F"},"geometry":{"type":"Point","coordinates":[-75029,45684]}},{"type":"Feature","properties":{"referenceFormID":"0011109F"},"geometry":{"type":"Point","coordinates":[-82465,85273]}},{"type":"Feature","properties":{"referenceFormID":"0011109F"},"geometry":{"type":"Point","coordinates":[-92562,205585]}},{"type":"Feature","properties":{"referenceFormID":"0011109F"},"geometry":{"type":"Point","coordinates":[-23982,-168140]}},{"type":"Feature","properties":{"referenceFormID":"0011109F"},"geometry":{"type":"Point","coordinates":[-129936,-61489]}},{"type":"Feature","properties":{"referenceFormID":"0011109F"},"geometry":{"type":"Point","coordinates":[-2048,-7805]}}]}
