{"type":"FeatureCollection","features":[{"type":"Feature","properties":{"referenceFormID":"00149E61"},"geometry":{"type":"Point","coordinates":[91027,20477]}},{"type":"Feature","properties":{"referenceFormID":"00149E61"},"geometry":{"type":"Point","coordinates":[31201,190847]}},{"type":"Feature","properties":{"referenceFormID":"00149E61"},"geometry":{"type":"Point","coordinates":[25540,202814]}},{"type":"Feature","properties":{"referenceFormID":"00149E61"},"geometry":{"type":"Point","coordinates":[172800,-146203]}},{"type":"Feature","properties":{"referenceFormID":"00149E61"},"geometry":{"type":"Point","coordinates":[184688,-4006]}},{"type":"Feature","properties":{"referenceFormID":"00149E61"},"geometry":{"type":"Point","coordinates":[-168526,194128]}},{"type":"Feature","properties":{"referenceFormID":"00149E61"},"geometry":{"type":"Point","coordinates":[-53210,89963]}},{"type":"Feature","properties":{"referenceFormID":"00149E61"},"geometry":{"type":"Point","coordinates":[-19727,30720]}},{"type":"Feature","properties":{"referenceFormID":"00149E61"},"geometry":{"type":"Point","coordinates":[-19916,32742]}},{"type":"Feature","properties":{"referenceFormID":"00149E61"},"geometry":{"type":"Point","coordinates":[-20149,32591]}},{"type":"Feature","properties":{"referenceFormID":"00149E61"},"geometry":{"type":"Point","coordinates":[-21168,31176]}},{"type":"Feature","properties":{"referenceFormID":"00149E61"},"geometry":{"type":"Point","coordinates":[-21604,32114]}},{"type":"Feature","properties":{"referenceFormID":"00149E61"},"geometry":{"type":"Point","coordinates":[-20948,29882]}},{"type":"Feature","properties":{"referenceFormID":"00149E61"},"geometry":{"type":"Point","coordinates":[-21418,29347]}},{"type":"Feature","properties":{"referenceFormID":"00149E61"},"geometry":{"type":"Point","coordinates":[-21377,29663]}},{"type":"Feature","properties":{"referenceFormID":"00149E61"},"geometry":{"type":"Point","coordinates":[-19967,32845]}},{"type":"Feature","properties":{"referenceFormID":"00149E61"},"geometry":{"type":"Point","coordinates":[-21170,37561]}},{"type":"Feature","properties":{"referenceFormID":"00149E61"},"geometry":{"type":"Point","coordinates":[-22210,37286]}},{"type":"Feature","properties":{"referenceFormID":"00149E61"},"geometry":{"type":"Point","coordinates":[-20497,36510]}},{"type":"Feature","properties":{"referenceFormID":"00149E61"},"geometry":{"type":"Point","coordinates":[-23115,35892]}},{"type":"Feature","properties":{"referenceFormID":"00149E61"},"geometry":{"type":"Point","coordinates":[-22408,35122]}},{"type":"Feature","properties":{"referenceFormID":"00149E61"},"geometry":{"type":"Point","coordinates":[-21344,34118]}},{"type":"Feature","properties":{"referenceFormID":"00149E61"},"geometry":{"type":"Point","coordinates":[-20663,34566]}},{"type":"Feature","properties":{"referenceFormID":"00149E61"},"geometry":{"type":"Point","coordinates":[-20499,33184]}},{"type":"Feature","properties":{"referenceFormID":"00149E61"},"geometry":{"type":"Point","coordinates":[-8692,105666]}},{"type":"Feature","properties":{"referenceFormID":"00149E61"},"geometry":{"type":"Point","coordinates":[-8778,105997]}},{"type":"Feature","properties":{"referenceFormID":"00149E61"},"geometry":{"type":"Point","coordinates":[-103441,-139878]}},{"type":"Feature","properties":{"referenceFormID":"00149E61"},"geometry":{"type":"Point","coordinates":[-58309,-38509]}},{"type":"Feature","properties":{"referenceFormID":"00149E61"},"geometry":{"type":"Point","coordinates":[-59148,-57350]}}]}
