{"type":"FeatureCollection","features":[{"type":"Feature","properties":{"referenceFormID":"00190CB6"},"geometry":{"type":"Point","coordinates":[43942,178519]}},{"type":"Feature","properties":{"referenceFormID":"00190CB6"},"geometry":{"type":"Point","coordinates":[-168016,54789]}},{"type":"Feature","properties":{"referenceFormID":"00190CB6"},"geometry":{"type":"Point","coordinates":[-162702,-117144]}},{"type":"Feature","properties":{"referenceFormID":"00190CB6"},"geometry":{"type":"Point","coordinates":[57489,39332]}},{"type":"Feature","properties":{"referenceFormID":"00190CB6"},"geometry":{"type":"Point","coordinates":[157601,-88363]}},{"type":"Feature","properties":{"referenceFormID":"00190CB6"},"geometry":{"type":"Point","coordinates":[175120,51444]}},{"type":"Feature","properties":{"referenceFormID":"00190CB6"},"geometry":{"type":"Point","coordinates":[176150,137882]}},{"type":"Feature","properties":{"referenceFormID":"00190CB6"},"geometry":{"type":"Point","coordinates":[1528,150089]}},{"type":"Feature","properties":{"referenceFormID":"00190CB6"},"geometry":{"type":"Point","coordinates":[13438,110238]}},{"type":"Feature","properties":{"referenceFormID":"00190CB6"},"geometry":{"type":"Point","coordinates":[-57660,104665]}},{"type":"Feature","properties":{"referenceFormID":"00190CB6"},"geometry":{"type":"Point","coordinates":[-46258,154186]}},{"type":"Feature","properties":{"referenceFormID":"00190CB6"},"geometry":{"type":"Point","coordinates":[-126336,109806]}},{"type":"Feature","properties":{"referenceFormID":"00190CB6"},"geometry":{"type":"Point","coordinates":[-57996,160556]}},{"type":"Feature","properties":{"referenceFormID":"00190CB6"},"geometry":{"type":"Point","coordinates":[-58065,160834]}},{"type":"Feature","properties":{"referenceFormID":"00190CB6"},"geometry":{"type":"Point","coordinates":[-58590,160495]}},{"type":"Feature","properties":{"referenceFormID":"00190CB6"},"geometry":{"type":"Point","coordinates":[-94033,33919]}}]}
