{"type":"FeatureCollection","features":[{"type":"Feature","properties":{"referenceFormID":"003A5E7E","primitiveShape":"Box","boundX":64,"boundY":820},"geometry":{"type":"Polygon","coordinates":[[[152134,89225],[152198,89225],[152198,90045],[152134,90045],[152134,89225]]]}},{"type":"Feature","properties":{"referenceFormID":"003A5E7E","primitiveShape":"Box","boundX":64,"boundY":820},"geometry":{"type":"Polygon","coordinates":[[[152512,89596],[152576,89596],[152576,90416],[152512,90416],[152512,89596]]]}},{"type":"Feature","properties":{"referenceFormID":"003A5E7E","primitiveShape":"Box","boundX":64,"boundY":820},"geometry":{"type":"Polygon","coordinates":[[[152141,89975],[152205,89975],[152205,90795],[152141,90795],[152141,89975]]]}},{"type":"Feature","properties":{"referenceFormID":"003A5E7E","primitiveShape":"Box","boundX":64,"boundY":820},"geometry":{"type":"Polygon","coordinates":[[[151762,89603],[151826,89603],[151826,90423],[151762,90423],[151762,89603]]]}}]}
