{"type":"FeatureCollection","features":[{"type":"Feature","properties":{"referenceFormID":"0042C565","primitiveShape":"Box","boundX":128,"boundY":128},"geometry":{"type":"Polygon","coordinates":[[43089,14739],[43217,14739],[43089,14867],[43217,14867]]}},{"type":"Feature","properties":{"referenceFormID":"0042C565","primitiveShape":"Box","boundX":128,"boundY":128},"geometry":{"type":"Polygon","coordinates":[[39116,18418],[39244,18418],[39116,18546],[39244,18546]]}},{"type":"Feature","properties":{"referenceFormID":"0042C565","primitiveShape":"Box","boundX":128,"boundY":128},"geometry":{"type":"Polygon","coordinates":[[39126,10404],[39254,10404],[39126,10532],[39254,10532]]}},{"type":"Feature","properties":{"referenceFormID":"0042C565","primitiveShape":"Box","boundX":128,"boundY":128},"geometry":{"type":"Polygon","coordinates":[[35128,14436],[35256,14436],[35128,14564],[35256,14564]]}}]}
